_version.py
openawsem/__init__.py
openawsem/_version.py
openawsem/config.ini
openawsem/openAWSEM.py
openawsem/data/database/cullpdb_pc80_res3.0_R1.0_d160504_chains29712
openawsem/data/database/cullpdb_pc80_res3.0_R1.0_d160504_chains29712.fasta
openawsem/data/database/cullpdb_pc80_res3.0_R1.0_d160504_chains29712.phr
openawsem/data/database/cullpdb_pc80_res3.0_R1.0_d160504_chains29712.pin
openawsem/data/database/cullpdb_pc80_res3.0_R1.0_d160504_chains29712.psq
openawsem/functionTerms/__init__.py
openawsem/functionTerms/basicTerms.py
openawsem/functionTerms/biasTerms.py
openawsem/functionTerms/constraints.py
openawsem/functionTerms/contactTerms.py
openawsem/functionTerms/debyeHuckelTerms.py
openawsem/functionTerms/hydrogenBondTerms.py
openawsem/functionTerms/membraneTerms.py
openawsem/functionTerms/templateTerms.py
openawsem/helperFunctions/DataPath.py
openawsem/helperFunctions/IndexPdb.py
openawsem/helperFunctions/MultCha_prepFrags_index.py
openawsem/helperFunctions/Pdb2Gro.py
openawsem/helperFunctions/Pdb2GroLib.py
openawsem/helperFunctions/__init__.py
openawsem/helperFunctions/contactMapFromOpenMMTrajectory.py
openawsem/helperFunctions/convertOpenmmTrajectoryToStandardMovie.py
openawsem/helperFunctions/create_debyeHuckel.py
openawsem/helperFunctions/create_fragment_memory.py
openawsem/helperFunctions/create_single_memory.py
openawsem/helperFunctions/fasta2pdb.py
openawsem/helperFunctions/myFunctions.py
openawsem/helperFunctions/myFunctions_helper.py
openawsem/helperFunctions/stride2ssweight.py
openawsem/parameters/__init__.py
openawsem/parameters/anti_HB
openawsem/parameters/anti_NHB
openawsem/parameters/anti_one
openawsem/parameters/burial_gamma.dat
openawsem/parameters/cbd_cbd_real_contact_symmetric.csv
openawsem/parameters/gamma.dat
openawsem/parameters/membrane_gamma.dat
openawsem/parameters/membrane_gamma_original.dat
openawsem/parameters/membrane_gamma_original_x200.dat
openawsem/parameters/membrane_gamma_rescaled.dat
openawsem/parameters/para_HB
openawsem-1.1.1.dist-info/LICENSE
openawsem-1.1.1.dist-info/METADATA
openawsem-1.1.1.dist-info/WHEEL
openawsem-1.1.1.dist-info/entry_points.txt
openawsem-1.1.1.dist-info/top_level.txt
openawsem-1.1.1.dist-info/RECORD
