Metadata-Version: 2.1
Name: openawsem
Version: 1.1.1
Summary: Calculates single residue frustration, and mutational frustration of proteins.
Home-page: https://openawsem.org/
Author: Carlos Bueno
Author-email: carlos.bueno@rice.edu
License: MIT
Requires-Python: >=3.8
License-File: LICENSE
Requires-Dist: biopython
Requires-Dist: matplotlib
Requires-Dist: numpy
Requires-Dist: pandas
Requires-Dist: openmm
Requires-Dist: pdbfixer
Requires-Dist: mdtraj
